odoo/addons/sale_order_transmit_method/README.rst
odoo/addons/sale_order_transmit_method/__init__.py
odoo/addons/sale_order_transmit_method/__manifest__.py
odoo/addons/sale_order_transmit_method/i18n/ca.po
odoo/addons/sale_order_transmit_method/i18n/es.po
odoo/addons/sale_order_transmit_method/i18n/sale_order_transmit_method.pot
odoo/addons/sale_order_transmit_method/models/__init__.py
odoo/addons/sale_order_transmit_method/models/sale_order.py
odoo/addons/sale_order_transmit_method/readme/CONTRIBUTORS.rst
odoo/addons/sale_order_transmit_method/readme/DESCRIPTION.rst
odoo/addons/sale_order_transmit_method/static/description/icon.png
odoo/addons/sale_order_transmit_method/static/description/index.html
odoo/addons/sale_order_transmit_method/tests/__init__.py
odoo/addons/sale_order_transmit_method/tests/test_sale_order.py
odoo/addons/sale_order_transmit_method/views/sale_order.xml
odoo/addons/sale_order_transmit_method/wizards/__init__.py
odoo/addons/sale_order_transmit_method/wizards/sale_advance_payment_inv.py
odoo12_addon_sale_order_transmit_method-12.0.1.0.0.99.dev10.dist-info/METADATA
odoo12_addon_sale_order_transmit_method-12.0.1.0.0.99.dev10.dist-info/WHEEL
odoo12_addon_sale_order_transmit_method-12.0.1.0.0.99.dev10.dist-info/top_level.txt
odoo12_addon_sale_order_transmit_method-12.0.1.0.0.99.dev10.dist-info/RECORD
